pyflyby/__init__.py
pyflyby/__main__.py
pyflyby/_autoimp.py
pyflyby/_cmdline.py
pyflyby/_comms.py
pyflyby/_dbg.py
pyflyby/_dynimp.py
pyflyby/_fast_iter_modules.cpython-312-x86_64-linux-musl.so
pyflyby/_file.py
pyflyby/_flags.py
pyflyby/_format.py
pyflyby/_idents.py
pyflyby/_import_sorting.py
pyflyby/_importclns.py
pyflyby/_importdb.py
pyflyby/_imports2s.py
pyflyby/_importstmt.py
pyflyby/_interactive.py
pyflyby/_livepatch.py
pyflyby/_log.py
pyflyby/_modules.py
pyflyby/_parse.py
pyflyby/_py.py
pyflyby/_saveframe.py
pyflyby/_saveframe_reader.py
pyflyby/_util.py
pyflyby/_version.py
pyflyby/autoimport.py
pyflyby/check_parse.py
pyflyby/importdb.py
pyflyby/etc/pyflyby/canonical.py
pyflyby/etc/pyflyby/common.py
pyflyby/etc/pyflyby/forget.py
pyflyby/etc/pyflyby/mandatory.py
pyflyby/etc/pyflyby/numpy.py
pyflyby/etc/pyflyby/std.py
pyflyby/libexec/pyflyby/colordiff
pyflyby/libexec/pyflyby/diff-colorize
pyflyby/share/emacs/site-lisp/pyflyby.el
pyflyby-1.10.5.data/scripts/collect-exports
pyflyby-1.10.5.data/scripts/collect-imports
pyflyby-1.10.5.data/scripts/find-import
pyflyby-1.10.5.data/scripts/prune-broken-imports
pyflyby-1.10.5.data/scripts/pyflyby-diff
pyflyby-1.10.5.data/scripts/reformat-imports
pyflyby-1.10.5.data/scripts/replace-star-imports
pyflyby-1.10.5.data/scripts/saveframe
pyflyby-1.10.5.data/scripts/tidy-imports
pyflyby-1.10.5.data/scripts/transform-imports
pyflyby.libs/libgcc_s-0cd532bd.so.1
pyflyby.libs/libstdc++-5d72f927.so.6.0.33
pyflyby-1.10.5.dist-info/METADATA
pyflyby-1.10.5.dist-info/WHEEL
pyflyby-1.10.5.dist-info/entry_points.txt
pyflyby-1.10.5.dist-info/RECORD
pyflyby-1.10.5.dist-info/licenses/LICENSE.txt
pyflyby-1.10.5.dist-info/sboms/auditwheel.cdx.json
