Metadata-Version: 2.4
Name: pyflyby
Version: 1.10.5
Summary: pyflyby - Python development productivity tools, in particular automatic import management
Author-Email: Karl Chen <quarl@8166.clguba.z.quarl.org>
License-Expression: MIT
License-File: LICENSE.txt
Classifier: Programming Language :: Python
Classifier: Topic :: Software Development
Classifier: Topic :: Software Development :: Code Generators
Classifier: Topic :: Software Development :: Interpreters
Classifier: Intended Audience :: Developers
Classifier: Operating System :: OS Independent
Project-URL: Homepage, https://pypi.org/project/pyflyby/
Project-URL: Documentation, https://deshaw.github.io/pyflyby/
Project-URL: Source, https://github.com/deshaw/pyflyby
Requires-Python: >=3.10
Requires-Dist: black
Requires-Dist: tomli; python_version < "3.11"
Requires-Dist: typing_extensions>=4.6; python_version < "3.12"
Requires-Dist: prompt_toolkit
Requires-Dist: platformdirs
Provides-Extra: test
Requires-Dist: beartype; extra == "test"
Requires-Dist: build; extra == "test"
Requires-Dist: coverage; extra == "test"
Requires-Dist: flaky; extra == "test"
Requires-Dist: hypothesis; extra == "test"
Requires-Dist: ipykernel>=5.4.3; extra == "test"
Requires-Dist: ipython; extra == "test"
Requires-Dist: jupyter; extra == "test"
Requires-Dist: jupyter_console>=6.2; extra == "test"
Requires-Dist: notebook<6.1; extra == "test"
Requires-Dist: pexpect>=3.3; extra == "test"
Requires-Dist: pytest-cov; extra == "test"
Requires-Dist: pytest-json-report; extra == "test"
Requires-Dist: pytest<=8; extra == "test"
Requires-Dist: requests; extra == "test"
